<?xml version="1.0" encoding="utf-8" ?>
<Defs>
  <HeadTypeDef ParentName="AverageBase">
		<defName>PNHeadA</defName>
		<label>A</label>
		<graphicPath>Paniel/Heads/PNHead/PNHead1</graphicPath>
		<gender>None</gender>
	</HeadTypeDef>

  <HeadTypeDef ParentName="AverageBase">
		<defName>PNHeadB</defName>
		<label>B</label>
		<graphicPath>Paniel/Heads/PNHead/PNHead2</graphicPath>
		<gender>None</gender>
	</HeadTypeDef>

  <HeadTypeDef ParentName="AverageBase">
		<defName>PNHeadC</defName>
		<label>C</label>
		<graphicPath>Paniel/Heads/PNHead/PNHead3</graphicPath>
		<gender>None</gender>
	</HeadTypeDef>

  <HeadTypeDef ParentName="AverageBase">
		<defName>PNHeadD</defName>
		<label>D</label>
		<graphicPath>Paniel/Heads/PNHead/PNHead4</graphicPath>
		<gender>None</gender>
	</HeadTypeDef>

  <HeadTypeDef ParentName="AverageBase">
		<defName>PNHeadE</defName>
		<label>E</label>
		<graphicPath>Paniel/Heads/PNHead/PNHead5</graphicPath>
		<gender>None</gender>
	</HeadTypeDef>

  <HeadTypeDef ParentName="AverageBase">
		<defName>PNHeadF</defName>
		<label>F</label>
		<graphicPath>Paniel/Heads/PNHead/PNHead6</graphicPath>
		<gender>None</gender>
	</HeadTypeDef>

  <HeadTypeDef ParentName="AverageBase">
		<defName>PNHeadG</defName>
		<label>G</label>
		<graphicPath>Paniel/Heads/PNHead/PNHead7</graphicPath>
		<gender>None</gender>
	</HeadTypeDef>

  <HeadTypeDef ParentName="AverageBase">
		<defName>PNHeadH</defName>
		<label>H</label>
		<graphicPath>Paniel/Heads/PNHead/PNHead8</graphicPath>
		<gender>None</gender>
	</HeadTypeDef>

  <HeadTypeDef ParentName="AverageBase">
		<defName>PNHeadI</defName>
		<label>I</label>
		<graphicPath>Paniel/Heads/PNHead/PNHead9</graphicPath>
		<gender>None</gender>
	</HeadTypeDef>

  <HeadTypeDef ParentName="AverageBase">
		<defName>PNHeadJ</defName>
		<label>J</label>
		<graphicPath>Paniel/Heads/PNHead/PNHead10</graphicPath>
		<gender>None</gender>
	</HeadTypeDef>

  <HeadTypeDef ParentName="AverageBase">
		<defName>PNHeadK</defName>
		<label>K</label>
		<graphicPath>Paniel/Heads/PNHead/PNHead11</graphicPath>
		<gender>None</gender>
	</HeadTypeDef>

  <HeadTypeDef ParentName="AverageBase">
		<defName>PNHeadL</defName>
		<label>L</label>
		<graphicPath>Paniel/Heads/PNHead/PNHead12</graphicPath>
		<gender>None</gender>
	</HeadTypeDef>
</Defs>